etl_lib/__init__.py
etl_lib/cli/__init__.py
etl_lib/cli/run_tools.py
etl_lib/core/BatchProcessor.py
etl_lib/core/ClosedLoopBatchProcessor.py
etl_lib/core/ETLContext.py
etl_lib/core/ParallelBatchProcessor.py
etl_lib/core/ProgressReporter.py
etl_lib/core/SplittingBatchProcessor.py
etl_lib/core/Task.py
etl_lib/core/ValidationBatchProcessor.py
etl_lib/core/__init__.py
etl_lib/core/utils.py
etl_lib/data_sink/CSVBatchSink.py
etl_lib/data_sink/CypherBatchSink.py
etl_lib/data_sink/SQLBatchSink.py
etl_lib/data_sink/__init__.py
etl_lib/data_source/CSVBatchSource.py
etl_lib/data_source/CypherBatchSource.py
etl_lib/data_source/SQLBatchSource.py
etl_lib/data_source/__init__.py
etl_lib/task/CreateReportingConstraintsTask.py
etl_lib/task/ExecuteCypherTask.py
etl_lib/task/GDSTask.py
etl_lib/task/__init__.py
etl_lib/task/data_loading/CSVLoad2Neo4jTask.py
etl_lib/task/data_loading/ParallelCSVLoad2Neo4jTask.py
etl_lib/task/data_loading/ParallelSQLLoad2Neo4jTask.py
etl_lib/task/data_loading/SQLLoad2Neo4jTask.py
etl_lib/task/data_loading/__init__.py
etl_lib/test_utils/__init__.py
etl_lib/test_utils/utils.py
neo4j_etl_lib-0.3.0.dist-info/licenses/LICENSE
neo4j_etl_lib-0.3.0.dist-info/WHEEL
neo4j_etl_lib-0.3.0.dist-info/METADATA
neo4j_etl_lib-0.3.0.dist-info/RECORD
